README.rst
setup.cfg
setup.py
multilog/__init__.py
multilog/handlers.py
multilog/receivers.py
multilog.egg-info/PKG-INFO
multilog.egg-info/SOURCES.txt
multilog.egg-info/dependency_links.txt
multilog.egg-info/entry_points.txt
multilog.egg-info/requires.txt
multilog.egg-info/top_level.txt
multilog.egg-info/zip-safe
multilog/scripts/__init__.py
multilog/scripts/cli.py