Metadata-Version: 1.1
Name: multilog
Version: 0.9.0
Summary: A simple logger for multiple Python processes.
Home-page: https://github.com/humangeo/multilog
Author: Aru Sahni
Author-email: aru@thehumangeo.com
License: MIT
Keywords: server multiprocess multiproc parallel logger logging logs
Platform: UNKNOWN
Classifier: Development Status :: 5 - Production/Stable
Classifier: Environment :: No Input/Output (Daemon)
Classifier: Intended Audience :: Developers
Classifier: License :: OSI Approved :: MIT License
Classifier: Operating System :: POSIX
Classifier: Programming Language :: Python :: 3 :: Only
Classifier: Topic :: System :: Logging
